{
  "type": "script",
  "seleniumVersion": "2",
  "formatVersion": 1,
  "steps": [
    {
      "type": "get",
      "url": "https://ignite.where2stageit.com/login.html"
    },
    {
      "type": "setElementText",
      "locator": {
        "type": "id",
        "value": "loginid"
      },
      "text": "qa_tester"
    },
    {
      "type": "setElementText",
      "locator": {
        "type": "id",
        "value": "password"
      },
      "text": "Where2getit!"
    },
    {
      "type": "clickElement",
      "locator": {
        "type": "id",
        "value": "submit"
      }
    },
    {
      "type": "clickElement",
      "locator": {
        "type": "css selector",
        "value": "b"
      }
    },
    {
      "type": "clickElement",
      "locator": {
        "type": "id",
        "value": "accounts_chzn_o_0"
      }
    },
    {
      "type": "clickElement",
      "locator": {
        "type": "id",
        "value": "btn-select-account"
      }
    },
    {
      "type": "verifyTextPresent",
      "text": "Launchpad"
    },
    {
      "type": "verifyElementValue",
      "locator": {
        "type": "id",
        "value": "date-range"
      },
      "value": "09/12/2013 - 09/22/2013"
    },
    {
      "type": "verifyTextPresent",
      "text": "Total Channel Performance Across TimeDate Range: 09/12/2013 - 09/22/2013"
    },
    {
      "type": "clickElement",
      "locator": {
        "type": "id",
        "value": "change-chart"
      }
    },
    {
      "type": "clickElement",
      "locator": {
        "type": "id",
        "value": "change-chart"
      }
    },
    {
      "type": "verifyTextPresent",
      "text": "Channels Performance Date Range: 09/12/2013 - 09/22/2013"
    },
    {
      "type": "verifyTextPresent",
      "text": "Channels Page Views ConversionsAny user action listed under Report Settings can be turned into a conversion by checking the Conversion RateConversion rate is calculated by dividing count"
    },
    {
      "type": "verifyTextPresent",
      "text": "web 0 0% ↑ 2,085 -17% ↓ 0.00% 0% ↑ $0.00 0% ↑"
    },
    {
      "type": "verifyTextPresent",
      "text": "search 0 0% ↑ 0 0% ↑ 0% 0% ↑ $0 0% ↑"
    },
    {
      "type": "verifyTextPresent",
      "text": "mobile 0 0% ↑ 0 0% ↑ 0% 0% ↑ $0 0% ↑"
    },
    {
      "type": "verifyTextPresent",
      "text": "social 0 0% ↑ 0 0% ↑ 0% 0% ↑ $0 0% ↑"
    },
    {
      "type": "verifyTextPresent",
      "text": "Totals02,0850.00%$0.00"
    },
    {
      "type": "verifyTextPresent",
      "text": "Totals02,0850.00%$0.00"
    },
    {
      "type": "verifyTextPresent",
      "text": "Website Missing Locations Bad Addresses Bad Phone Numbers Poor Geocodes Duplicates"
    },
    {
      "type": "verifyElementPresent",
      "locator": {
        "type": "css selector",
        "value": "strong.g-foursquare"
      }
    },
    {
      "type": "verifyElementPresent",
      "locator": {
        "type": "css selector",
        "value": "strong.g-google"
      }
    },
    {
      "type": "verifyElementPresent",
      "locator": {
        "type": "css selector",
        "value": "strong.g-facebook"
      }
    },
    {
      "type": "verifyElementPresent",
      "locator": {
        "type": "css selector",
        "value": "strong.g-yahoo"
      }
    },
    {
      "type": "verifyTextPresent",
      "text": "Total 0 0 0% ↑ 0 0 0% ↑ 0 0 0% ↑"
    }
  ]
}